django_polymorphic_queryset-0.2.1.dist-info/METADATA
django_polymorphic_queryset-0.2.1.dist-info/RECORD
django_polymorphic_queryset-0.2.1.dist-info/WHEEL
django_polymorphic_queryset-0.2.1.dist-info/top_level.txt
polymorphic_queryset/__init__.py
polymorphic_queryset/tests/__init__.py
polymorphic_queryset/tests/models.py
polymorphic_queryset/tests/test_queries.py
polymorphic_queryset/tests/migrations/0001_initial.py
polymorphic_queryset/tests/migrations/__init__.py
