Metadata-Version: 2.1
Name: django-polymorphic-queryset
Version: 0.2.1
Summary: Polymorphic inheritance for Django QuerySet
Home-page: https://github.com/Nerlin/django-polymorphic-queryset
Author: Artem Yastrebkov
Author-email: nerlin57@gmail.com
License: UNKNOWN
Platform: UNKNOWN
Classifier: Development Status :: 4 - Beta
Classifier: Environment :: Web Environment
Classifier: Framework :: Django
Classifier: Framework :: Django :: 1.9
Classifier: Framework :: Django :: 1.10
Classifier: Framework :: Django :: 1.11
Classifier: Framework :: Django :: 2.0
Classifier: Intended Audience :: Developers
Classifier: Operating System :: OS Independent
Classifier: Programming Language :: Python :: 3
Classifier: Programming Language :: Python :: 3.4
Classifier: Programming Language :: Python :: 3.5
Classifier: Programming Language :: Python :: 3.6
Classifier: Topic :: Database
Requires-Dist: Django (>=1.9)
